escpos/__init__.py
escpos/connections.py
escpos/commandset/__init__.py
escpos/commandset/generic.py
python_printer_escpos-0.0.4.dist-info/METADATA
python_printer_escpos-0.0.4.dist-info/WHEEL
python_printer_escpos-0.0.4.dist-info/namespace_packages.txt
python_printer_escpos-0.0.4.dist-info/top_level.txt
python_printer_escpos-0.0.4.dist-info/zip-safe
python_printer_escpos-0.0.4.dist-info/RECORD
